pychatai/__init__.py
pychatai/gpt.py
py_chatai-1.0.4.dist-info/LICENSE
py_chatai-1.0.4.dist-info/METADATA
py_chatai-1.0.4.dist-info/WHEEL
py_chatai-1.0.4.dist-info/top_level.txt
py_chatai-1.0.4.dist-info/RECORD
